setup.py
ppe/__init__.py
ppe/python.py
ppe.egg-info/PKG-INFO
ppe.egg-info/SOURCES.txt
ppe.egg-info/dependency_links.txt
ppe.egg-info/not-zip-safe
ppe.egg-info/top_level.txt