Metadata-Version: 1.0
Name: ppe
Version: 1.4
Summary: Magic_Addition
Home-page: UNKNOWN
Author: UNKNOWN
Author-email: UNKNOWN
License: UNKNOWN
Platform: UNKNOWN
